pulumi_duplocloud/__init__.py
pulumi_duplocloud/_inputs.py
pulumi_duplocloud/_utilities.py
pulumi_duplocloud/admin_system_setting.py
pulumi_duplocloud/asg_profile.py
pulumi_duplocloud/aws_api_gateway_integration.py
pulumi_duplocloud/aws_apigateway_event.py
pulumi_duplocloud/aws_appautoscaling_policy.py
pulumi_duplocloud/aws_appautoscaling_target.py
pulumi_duplocloud/aws_batch_compute_environment.py
pulumi_duplocloud/aws_batch_job_definition.py
pulumi_duplocloud/aws_batch_job_queue.py
pulumi_duplocloud/aws_batch_scheduling_policy.py
pulumi_duplocloud/aws_cloudfront_distribution.py
pulumi_duplocloud/aws_cloudwatch_event_rule.py
pulumi_duplocloud/aws_cloudwatch_event_target.py
pulumi_duplocloud/aws_cloudwatch_metric_alarm.py
pulumi_duplocloud/aws_dynamodb_table.py
pulumi_duplocloud/aws_dynamodb_table_v2.py
pulumi_duplocloud/aws_ecr_repository.py
pulumi_duplocloud/aws_efs_file_system.py
pulumi_duplocloud/aws_efs_lifecycle_policy.py
pulumi_duplocloud/aws_elasticsearch.py
pulumi_duplocloud/aws_host.py
pulumi_duplocloud/aws_kafka_cluster.py
pulumi_duplocloud/aws_lambda_function.py
pulumi_duplocloud/aws_lambda_function_event_config.py
pulumi_duplocloud/aws_lambda_permission.py
pulumi_duplocloud/aws_launch_template.py
pulumi_duplocloud/aws_launch_template_default_version.py
pulumi_duplocloud/aws_lb_listener_rule.py
pulumi_duplocloud/aws_lb_target_group.py
pulumi_duplocloud/aws_load_balancer.py
pulumi_duplocloud/aws_load_balancer_listener.py
pulumi_duplocloud/aws_mwaa_environment.py
pulumi_duplocloud/aws_rds_tag.py
pulumi_duplocloud/aws_sns_topic.py
pulumi_duplocloud/aws_sqs_queue.py
pulumi_duplocloud/aws_ssm_parameter.py
pulumi_duplocloud/aws_target_group_attributes.py
pulumi_duplocloud/aws_timestreamwrite_database.py
pulumi_duplocloud/aws_timestreamwrite_table.py
pulumi_duplocloud/azure_availability_set.py
pulumi_duplocloud/azure_datafactory.py
pulumi_duplocloud/azure_k8_node_pool.py
pulumi_duplocloud/azure_k8s_cluster.py
pulumi_duplocloud/azure_key_vault_secret.py
pulumi_duplocloud-1.0.1.dist-info/METADATA
pulumi_duplocloud-1.0.1.dist-info/WHEEL
pulumi_duplocloud-1.0.1.dist-info/top_level.txt
pulumi_duplocloud-1.0.1.dist-info/RECORD
