Metadata-Version: 2.4
Name: pulumi_duplocloud
Version: 1.0.1
Summary: A Pulumi package for creating and managing duplocloud cloud resources.
License: Apache-2.0
Project-URL: Homepage, https://duplocloud.com
Project-URL: Repository, https://github.com/duplocloud/pulumi-duplocloud
Keywords: pulumi,duplocloud,category/cloud
Requires-Python: >=3.9
Requires-Dist: parver>=0.2.1
Requires-Dist: pulumi<4.0.0,>=3.142.0
Requires-Dist: semver>=2.8.1
Requires-Dist: typing-extensions>=4.11; python_version < "3.11"
